botococe/__init__.py
botococe-0.1.0.dist-info/licenses/LICENSE
botococe-0.1.0.dist-info/METADATA
botococe-0.1.0.dist-info/WHEEL
botococe-0.1.0.dist-info/top_level.txt
botococe-0.1.0.dist-info/RECORD
